datasette_app_support/__init__.py
datasette_app_support/utils.py
datasette_app_support/static/sticky-footer.css
datasette_app_support/templates/_table-table-plugin_directory-plugins.html
datasette_app_support/templates/database.html
datasette_app_support/templates/index.html
datasette_app_support/templates/table-plugin_directory-plugins.html
datasette_app_support-0.11.8.dist-info/METADATA
datasette_app_support-0.11.8.dist-info/WHEEL
datasette_app_support-0.11.8.dist-info/entry_points.txt
datasette_app_support-0.11.8.dist-info/top_level.txt
datasette_app_support-0.11.8.dist-info/RECORD
