Metadata-Version: 2.1
Name: datasette-app-support
Version: 0.11.8
Summary: Part of https://github.com/simonw/datasette-app
Home-page: https://github.com/simonw/datasette-app-support
Author: Simon Willison
License: Apache License, Version 2.0
Project-URL: Issues, https://github.com/simonw/datasette-app-support/issues
Project-URL: CI, https://github.com/simonw/datasette-app-support/actions
Project-URL: Changelog, https://github.com/simonw/datasette-app-support/releases
Platform: UNKNOWN
Requires-Python: >=3.6
Requires-Dist: datasette (>=0.59)
Requires-Dist: sqlite-utils
Requires-Dist: packaging
Provides-Extra: test
Requires-Dist: pytest ; extra == 'test'
Requires-Dist: pytest-asyncio ; extra == 'test'
Requires-Dist: black ; extra == 'test'
Requires-Dist: pytest-httpx ; extra == 'test'
